setup.py
stormkafkamon/__init__.py
stormkafkamon/monitor.py
stormkafkamon/processor.py
stormkafkamon/zkclient.py
stormkafkamon.egg-info/PKG-INFO
stormkafkamon.egg-info/SOURCES.txt
stormkafkamon.egg-info/dependency_links.txt
stormkafkamon.egg-info/entry_points.txt
stormkafkamon.egg-info/requires.txt
stormkafkamon.egg-info/top_level.txt
stormkafkamon.egg-info/zip-safe