Metadata-Version: 1.0
Name: stormkafkamon
Version: 0.1.1
Summary: Monitor offsets of a storm kafka spout.
Home-page: https://github.com/vivekrao1985/stormkafkamon
Author: Philip O'Toole
Author-email: philipomailbox-github@yahoo.com
License: Apache
Platform: any
